reghelp_client/__init__.py
reghelp_client/client.py
reghelp_client/exceptions.py
reghelp_client/models.py
reghelp_client/py.typed
reghelp_client-1.3.1.dist-info/LICENSE
reghelp_client-1.3.1.dist-info/METADATA
reghelp_client-1.3.1.dist-info/WHEEL
reghelp_client-1.3.1.dist-info/top_level.txt
reghelp_client-1.3.1.dist-info/RECORD
